toc_trade_pb/__init__.py
toc_trade_pb/app/__init__.py
toc_trade_pb/app/app_pb2.py
toc_trade_pb/app/app_pb2.pyi
toc_trade_pb/app/app_pb2_grpc.py
toc_trade_pb/forwarder/__init__.py
toc_trade_pb/forwarder/basic_pb2.py
toc_trade_pb/forwarder/basic_pb2.pyi
toc_trade_pb/forwarder/basic_pb2_grpc.py
toc_trade_pb/forwarder/entity_pb2.py
toc_trade_pb/forwarder/entity_pb2.pyi
toc_trade_pb/forwarder/entity_pb2_grpc.py
toc_trade_pb/forwarder/history_pb2.py
toc_trade_pb/forwarder/history_pb2.pyi
toc_trade_pb/forwarder/history_pb2_grpc.py
toc_trade_pb/forwarder/mq_pb2.py
toc_trade_pb/forwarder/mq_pb2.pyi
toc_trade_pb/forwarder/mq_pb2_grpc.py
toc_trade_pb/forwarder/realtime_pb2.py
toc_trade_pb/forwarder/realtime_pb2.pyi
toc_trade_pb/forwarder/realtime_pb2_grpc.py
toc_trade_pb/forwarder/subscribe_pb2.py
toc_trade_pb/forwarder/subscribe_pb2.pyi
toc_trade_pb/forwarder/subscribe_pb2_grpc.py
toc_trade_pb/forwarder/trade_pb2.py
toc_trade_pb/forwarder/trade_pb2.pyi
toc_trade_pb/forwarder/trade_pb2_grpc.py
toc_trade_pb_v2-0.1.11.dist-info/METADATA
toc_trade_pb_v2-0.1.11.dist-info/WHEEL
toc_trade_pb_v2-0.1.11.dist-info/licenses/LICENSE
toc_trade_pb_v2-0.1.11.dist-info/RECORD
