Metadata-Version: 2.3
Name: toc-trade-pb-v2
Version: 0.1.11
Summary: Pre-compiled Python protobuf files for ToC Trade
Project-URL: Homepage, https://github.com/ToC-Taiwan/toc-trade-protobuf
Project-URL: Issues, https://github.com/ToC-Taiwan/toc-trade-protobuf/issues
Author-email: Tim Hsu <maochindada@gmail.com>
License-File: LICENSE
Classifier: Programming Language :: Python :: 3
Requires-Python: >=3.11
